sccli/Emitter.py
sccli/Parser.py
sccli/Socketcluster.py
sccli/__init__.py
socketcluster_minbin_client-0.1.4.dist-info/LICENSE.txt
socketcluster_minbin_client-0.1.4.dist-info/METADATA
socketcluster_minbin_client-0.1.4.dist-info/WHEEL
socketcluster_minbin_client-0.1.4.dist-info/top_level.txt
socketcluster_minbin_client-0.1.4.dist-info/RECORD
