Metadata-Version: 2.1
Name: socketcluster-minbin-client
Version: 0.1.4
Summary: A client in Python to connect to socket cluster server with socket min bin codec
Home-page: https://bitbucket.tradex.vn/projects/TS/repos/socketcluster-min-bin-python
Author: techx
Author-email: devops@techx.vn
License: UNKNOWN
Platform: UNKNOWN
Classifier: Programming Language :: Python :: 3
Classifier: License :: OSI Approved :: MIT License
Classifier: Operating System :: OS Independent
Requires-Python: >=3.6
Requires-Dist: gevent (==20.5.2)
Requires-Dist: greenlet (==0.4.15)
Requires-Dist: msgpack (==1.0.0)
Requires-Dist: six (==1.15.0)
Requires-Dist: websocket-client-py3 (==0.15.0)
Requires-Dist: zope.event (==4.4)
Requires-Dist: zope.interface (==5.1.0)
